LICENSE
MANIFEST.in
README.md
setup.py
hybrid_methods/__init__.py
hybrid_methods/coherence/__init__.py
hybrid_methods/coherence/hybrid_screen.py
hybrid_methods/undulator/__init__.py
oasys_hybrid_methods.egg-info/PKG-INFO
oasys_hybrid_methods.egg-info/SOURCES.txt
oasys_hybrid_methods.egg-info/dependency_links.txt
oasys_hybrid_methods.egg-info/requires.txt
oasys_hybrid_methods.egg-info/top_level.txt
oasys_hybrid_methods.egg-info/zip-safe