Metadata-Version: 2.1
Name: oasys-hybrid-methods
Version: 1.0.2
Summary: Hybrid Methods, combining raytracing with wave optics
Home-page: https://github.com/oasys-kit/hybrid-methods
Download-URL: https://github.com/oasys-kit/hybrid-methods
Author: Luca Rebuffi, Xianbo Shi
Author-email: lrebuffi@anl.gov
Maintainer: Luca Rebuffi
Maintainer-email: lrebuffi@anl.gov
License: BSD
Keywords: x-raysynchrotron radiation,wavefront propagationray tracing,surface metrology,simulation
Classifier: Development Status :: 5 - Production/Stable
Classifier: Environment :: Console
Classifier: Environment :: Plugins
Classifier: Programming Language :: Python :: 3
Classifier: License :: OSI Approved :: GNU General Public License v3 or later (GPLv3+)
Classifier: Operating System :: POSIX
Classifier: Operating System :: Microsoft :: Windows
Classifier: Topic :: Scientific/Engineering :: Visualization
Classifier: Topic :: Software Development :: Libraries :: Python Modules
Classifier: Intended Audience :: Education
Classifier: Intended Audience :: Science/Research
Classifier: Intended Audience :: Developers
License-File: LICENSE
